listManager-1.0.dist-info/DESCRIPTION.rst
listManager-1.0.dist-info/METADATA
listManager-1.0.dist-info/RECORD
listManager-1.0.dist-info/WHEEL
listManager-1.0.dist-info/metadata.json
listManager-1.0.dist-info/top_level.txt
list_manager/__init__.py
list_manager/listmanager.py
